{"extracted_information": "该WEB内容详细分析了NFT市场（如OpenSea、Blur、Rarible等）如何通过核心策略和进一步改进来优化其性能、可扩展性和用户体验。文章涵盖了从链下订单管理、智能合约优化到前端基础设施优化的多方面技术实践，旨在提供低延迟、低成本和高效率的交易环境。", "specifications": {"技术栈/协议": ["IPFS (星际文件系统)", "WebP (图像格式)", "Elastic Search (搜索技术)", "WebSockets (实时通信)", "SSE (Server-Sent Events，服务器发送事件)", "OpenSea Seaport Protocol (智能合约协议)", "Commit-Reveal Schemes (拍卖机制)", "Batch Auction Systems (拍卖机制)", "PWAs (Progressive Web Apps，渐进式Web应用)", "SSR (Server-Side Rendering，服务器端渲染)", "Code Splitting (代码分割)", "Meta Transactions (元交易)", "RPC providers (如Infura, Alchemy)", "DAO-based governance models"], "区块链解决方案": ["Layer 2 Technologies (如Immutable X, Arbitrum, Optimism, Polygon)", "Blockchain Bridges (区块链桥)"], "优化技术概览": {"延迟加载": "仅在需要时加载NFT元数据，避免初始加载时间过长。", "图像格式优化": "使用高效的图像格式（如WebP）或压缩元数据文件，以减小存储大小并提高速度。", "CDN (内容分发网络)": "用于元数据分发和缓存层，减少后端服务器负载并加速内容交付。", "链下订单簿管理": "将订单簿保留在链下，仅在最终交易结算时与区块链交互，实现更快的匹配和查询，显著降低交易成本。", "智能合约优化": "针对交易结算进行优化，减少Gas使用，支持单次交易中完成多笔订单，并采用事件记录非必要数据、高级压缩技术存储元数据和订单信息。", "中继器和委托匹配": "用于高效订单匹配，特别适用于高频订单或竞价系统。", "改进的匹配算法": "优化匹配引擎以提供更好的推荐、快速订单匹配和动态定价（如优先处理最低价列表、即时买卖选项）。", "混合模型": "结合去中心化（区块链结算）和中心化（链下元数据存储、订单簿和API响应）组件。", "高效元数据管理": "IPFS缓存、元数据分片。", "动态定价和拍卖机制": "荷兰式拍卖、连续拍卖、时间敏感折扣。", "优化Gas使用": "批量铸造、Gas补贴。", "跨平台和跨链互操作性": "支持多条区块链、区块链桥、跨平台列表。", "优化搜索和发现": "高级过滤、个性化推荐。", "实时通知和更新": "价格/出价提醒、实时拍卖（通过WebSockets或SSE实现事件驱动架构）。", "高性能前端和后端基础设施": "前端（PWA、代码分割、SSR），后端（缓存层、优化API）。", "无Gas交易": "用户无需支付Gas费，由中继器代付。", "高级欺诈预防和安全": "身份验证（KYC）、来源验证、反抢购工具。"}}, "pricing": {"Gas费用优化": "通过链下订单簿、智能合约优化、Layer 2解决方案、批量铸造、Gas补贴、无Gas交易（Meta Transactions）等方式显著降低用户交易成本。"}, "features": [{"name": "链下订单簿管理", "description": "大多数NFT市场采用链下管理订单簿，仅在最终交易结算时与区块链互动，从而实现更快的订单匹配和查询，并显著降低用户的交易成本。", "examples": ["OpenSea (将列表存储在其数据库中)", "Blur (侧重于速度，适合专业交易者)"], "advantages": ["更快的匹配和查询", "显著降低交易成本"]}, {"name": "批量订单处理", "description": "并非NFT市场的标准方法，因为大多数交易是独立的且价值高昂。但某些市场会批量处理相关操作，例如空投或Gas高效的合约执行（如一次性上架多个NFT）。", "status": "部分采用"}, {"name": "智能合约交易结算优化", "description": "NFT市场高度优化智能合约以进行交易结算，减少Gas使用并支持复杂功能。", "details": ["OpenSea的Seaport协议：实现了高效的Gas使用，并支持在单笔交易中履行多笔订单。", "Blur：专注于高效的合约设计以降低高频交易者的成本。", "存储优化：对非必要数据采用事件记录而非持久状态存储；对元数据和订单信息采用高级压缩技术。"], "status": "高度优化"}, {"name": "Layer 2解决方案的应用", "description": "Layer 2技术被广泛用于扩展NFT交易，以降低成本并提高速度。", "examples": ["Immutable X：专为NFT构建的Layer 2解决方案，提供无Gas铸造和交易。", "Arbitrum和Optimism：与多个NFT市场集成，促进更便宜的交易。", "Polygon：OpenSea支持Polygon以实现Gas高效的NFT交易。"], "benefits": ["近乎即时交易", "成本仅为以太坊Layer 1的一小部分"], "status": "快速采用"}, {"name": "中继器和委托匹配", "description": "市场利用中继器进行高效的订单匹配，尤其是在处理高频订单或竞价系统时。", "example": "Blur使用先进的中继器为专业交易者提供低延迟订单匹配。"}, {"name": "改进的匹配算法", "description": "市场优化匹配引擎以提供更好的推荐、快速订单匹配和动态定价。", "priorities": ["最低价列表", "即时买/卖选项 (例如 Blur 的“地板清扫”)"]}, {"name": "降低抢先交易风险", "description": "市场通过特定机制解决抢先交易问题，以确保公平性。", "methods": ["提交-揭示方案 (用于拍卖)", "批量拍卖系统 (减少时序差异)"], "example": "Blur专注于提供最小化延迟的专业工具。"}, {"name": "混合模型", "description": "NFT市场融合了去中心化和中心化的组件，以结合两者的优势。", "details": ["去中心化结算：利用区块链进行交易最终确定。", "中心化基础设施：链下存储元数据、订单簿和快速API响应。", "混合协议：OpenSea的Seaport平衡了链上执行和链下订单存储；Blur大量使用链下系统以提高速度和用户体验。"], "status": "广泛采用"}, {"name": "市场做市商激励", "description": "市场激励流动性提供者和活跃交易者。", "examples": ["Blur：为有助于提供流动性的专业交易者提供代币奖励和激励。", "OpenSea：为批量或高频交易者提供费用减免和特别优惠。"]}, {"name": "网络层优化", "description": "市场探索整合网络优化措施。", "methods": ["与专用RPC提供商合作 (如Infura, Alchemy) 以降低延迟。", "使用内容分发网络 (CDNs) 进行元数据分发。", "分布式缓存以加速用户界面。"]}, {"name": "高效元数据管理", "description": "优化存储和访问元数据，特别是存储在IPFS或其他去中心化文件系统上的大量元数据。", "optimizations": ["IPFS缓存：使用缓存层或CDN网络加快元数据访问。", "延迟加载：仅在必要时加载NFT元数据，避免初始加载时间过长。", "优化文件格式：使用高效的图像格式（如WebP）或压缩元数据文件，以减小存储大小并提高速度。", "元数据分片：将元数据分散到不同的服务器或存储系统，以分散负载并减少延迟。"]}, {"name": "动态定价和拍卖机制", "description": "通过自动化价格调整来提高市场效率。", "mechanisms": ["荷兰式拍卖", "连续拍卖", "时间敏感折扣 (如闪购或基于折扣的定价)"]}, {"name": "铸造和交易的Gas使用优化", "description": "通过多种解决方案降低Gas费用，克服交易障碍。", "solutions": ["批量铸造：允许用户在单次交易中铸造多个NFT以节省Gas。", "优化智能合约：使用Gas高效的编码模式，避免冗余计算。", "Layer 2解决方案：集成L2扩展方案（如Immutable X, Arbitrum, Polygon）以降低铸造、购买和转移NFT相关的Gas费用。", "Gas补贴：部分市场（如OpenSea）可能会提供Gas补贴作为促销手段。"]}, {"name": "跨平台和跨链互操作性", "description": "支持跨链和跨平台集成以提高流动性和可达性。", "methods": ["跨链支持：支持多条区块链（如Ethereum, Polygon, Solana, Binance Smart Chain）。", "区块链桥：用于在不同区块链之间转移NFT。", "跨平台列表：允许用户同时在多个平台列出NFT，增加曝光和流动性。"]}, {"name": "搜索和发现优化", "description": "通过改进用户发现、过滤和排序NFT的方式，显著提升用户体验。", "optimizations": ["Elastic Search：使用高级搜索引擎快速索引和检索NFT列表。", "个性化推荐：根据用户行为和偏好推荐NFT，提高参与度。", "高级过滤：提供更细粒度的搜索过滤器（如稀有度、价格范围、创作者）。"]}, {"name": "实时通知和更新", "description": "通过实时通知提高用户参与度并简化买卖流程。", "features": ["价格提醒：当NFT价格低于特定阈值时通知用户。", "出价提醒：当列表收到出价或即将到期时通知卖家。", "实时拍卖：提供拍卖的实时更新（如当前出价和剩余时间）。", "事件驱动架构：使用WebSockets或服务器发送事件（SSE）进行实时通信。"]}, {"name": "高性能前端和后端基础设施", "description": "优化前端性能以确保流畅的用户体验，并提升后端API效率。", "frontend_optimizations": ["渐进式Web应用 (PWAs)：更快的加载时间、离线访问和改进的移动可用性。", "代码分割：将大型JavaScript包分割成更小的块，最小化初始加载时间。", "服务器端渲染 (SSR)：在服务器上预渲染页面，减少最终用户的加载时间。"], "backend_optimizations": ["缓存层：使用内容分发网络 (CDNs) 或边缘缓存减少后端服务器负载并加速内容交付。", "优化API：确保后端API高效，并具备适当的索引、过滤和缓存机制以处理大量流量。"]}, {"name": "无Gas交易 (Meta Transactions)", "description": "用户无需自己支付Gas费用即可与平台互动，由中继器代为提交交易并支付Gas费，提供更无缝的用户体验。"}, {"name": "高级欺诈预防和安全", "description": "加强信任和安全，尤其对于高价值NFT交易至关重要。", "measures": ["身份验证 (KYC)：部分市场对高价值交易实施身份验证以防止欺诈。", "来源验证：确保NFT的来源和历史可追溯和验证，防止伪造品或赃物出售。", "反抢购工具：防止自动化抢购（例如在拍卖最后一秒购买）以确保公平交易。"]}], "statistics": {}, "temporal_info": {"article_date": "2024年11月26日", "adoption_trends": {"Layer 2 Technologies": "快速采用"}}, "geographical_data": {}, "references": [{"title": "How Popular NFT Marketplaces Optimize Their Performance ?", "author": "Truong Phung", "source": "DEV Community", "date": "Nov 26, 2024"}]}